deew/__main__.py
deew/bitrates.py
deew/logos.py
deew/messages.py
deew/xml_base.py
deew-3.2.2.dist-info/entry_points.txt
deew-3.2.2.dist-info/LICENSE
deew-3.2.2.dist-info/METADATA
deew-3.2.2.dist-info/WHEEL
deew-3.2.2.dist-info/RECORD
