Metadata-Version: 2.3
Name: deew
Version: 3.2.2
Summary: Dolby Encoding Engine Wrapper
License: MIT
Author: pcroland
Author-email: pcroland@protonmail.ch
Requires-Python: >=3.10,<3.14
Classifier: License :: OSI Approved :: MIT License
Classifier: Programming Language :: Python :: 3
Classifier: Programming Language :: Python :: 3.10
Classifier: Programming Language :: Python :: 3.11
Classifier: Programming Language :: Python :: 3.12
Classifier: Programming Language :: Python :: 3.13
Requires-Dist: Unidecode (>=1.3.7,<2.0.0)
Requires-Dist: packaging (>=23.2,<24.0)
Requires-Dist: platformdirs (>=4.1.0,<5.0.0)
Requires-Dist: requests (>=2.31.0,<3.0.0)
Requires-Dist: rich (>=13.7.0,<14.0.0)
Requires-Dist: toml (>=0.10.2,<0.11.0)
Requires-Dist: xmltodict (>=0.13.0,<0.14.0)
